LICENSE
MANIFEST.in
README.rst
cocorahs_dlt.py
setup.py
CoCoRaHS_Download_Tool.egg-info/PKG-INFO
CoCoRaHS_Download_Tool.egg-info/SOURCES.txt
CoCoRaHS_Download_Tool.egg-info/dependency_links.txt
CoCoRaHS_Download_Tool.egg-info/top_level.txt