Metadata-Version: 1.1
Name: CoCoRaHS-Download-Tool
Version: 0.0.3
Summary: Tool to download CoCoRaHS data.
Home-page: https://bitbucket.org/nmclimate/cocorahs-download-tool
Author: Stanley Engle
Author-email: sengle@nmsu.edu
License: BSD License
Platform: UNKNOWN
Classifier: Intended Audience :: Developers
Classifier: License :: OSI Approved :: BSD License
Classifier: Operating System :: OS Independent
Classifier: Programming Language :: Python
Classifier: Programming Language :: Python :: 2.6
Classifier: Programming Language :: Python :: 2.7
